setup.py
m3u8ToMp4/__init__.py
m3u8ToMp4/api.py
m3u8ToMp4/exceptions.py
m3u8ToMp4/ffmpeg.exe
m3u8ToMp4/process.py
m3u8ToMp4/proxies_generate.py
m3u8ToMp4/session.py
m3u8ToMp4/utils.py
m3u8ToMp4.egg-info/PKG-INFO
m3u8ToMp4.egg-info/SOURCES.txt
m3u8ToMp4.egg-info/dependency_links.txt
m3u8ToMp4.egg-info/not-zip-safe
m3u8ToMp4.egg-info/requires.txt
m3u8ToMp4.egg-info/top_level.txt