Metadata-Version: 1.0
Name: m3u8ToMp4
Version: 0.2.3
Summary: download video by m3u8 url
Home-page: https://github.com/yfd-01/m3u8ToMp4
Author: VioletYFD
Author-email: 2448543261@qq.com
License: MIT
Platform: UNKNOWN
